keras_ctcmodel/CTCModel.py
keras_ctcmodel/__init__.py
keras_ctcmodel-1.0.0rc3.dist-info/LICENSE
keras_ctcmodel-1.0.0rc3.dist-info/METADATA
keras_ctcmodel-1.0.0rc3.dist-info/WHEEL
keras_ctcmodel-1.0.0rc3.dist-info/top_level.txt
keras_ctcmodel-1.0.0rc3.dist-info/RECORD
