Metadata-Version: 2.1
Name: keras-ctcmodel
Version: 1.0.0rc3
Summary: Easy-to-use Connectionnist Temporal Classification in Keras
Home-page: https://github.com/cyprienruffino/CTCModel
Author: Cyprien Ruffino
Author-email: ruffino.cyprien@gmail.com
License: UNKNOWN
Platform: UNKNOWN
Classifier: Programming Language :: Python :: 3
Classifier: License :: OSI Approved :: MIT License
Classifier: Operating System :: OS Independent
Classifier: Intended Audience :: Developers
Classifier: Intended Audience :: Science/Research
Classifier: Topic :: Scientific/Engineering :: Artificial Intelligence
Requires-Python: >=3.5
Requires-Dist: keras
Requires-Dist: tensorflow
